{
  "duration": 66.87000274658203,
  "language": "english",
  "text": "The trap snaps shut so quietly you won't even hear it. Manufacturing plants start simple. They lease a few Optimus units, run the numbers, and the bath is undeniable. Why pay humans $40 an hour when robots cost $8? So they scale up. 10 units become 100. 100 become 1,000. Then something shifts. Tesla adjusts the subscription model. Monthly fees climb 15%. Then 20. Factory owners grumble. But what's the alternative? Fire the machines and post-job listings? Retrain a human workforce that's moved on to other industries? The cost of switching back now exceeds the cost of staying locked in. This is the dependency spiral, and it's devastatingly effective. Every price increase gets absorbed because the pain of leaving hurts more than the pain of paying. Tesla doesn't need to own your factory. They just need to own something your factory cannot function without. The rent extraction phase has begun, and here's what makes it permanent. The longer you stay, the deeper you sink. Your human expertise erodes. Your alternatives vanish. You're not a customer anymore. You're a subscriber who forgot how to leave.",
  "segments": null,
  "usage": {
    "seconds": 67.0,
    "type": "duration"
  },
  "words": [
    {
      "end": 0.46000000834465027,
      "start": 0.0,
      "word": "The"
    },
    {
      "end": 0.5600000023841858,
      "start": 0.46000000834465027,
      "word": "trap"
    },
    {
      "end": 0.9800000190734863,
      "start": 0.5600000023841858,
      "word": "snaps"
    },
    {
      "end": 1.2799999713897705,
      "start": 0.9800000190734863,
      "word": "shut"
    },
    {
      "end": 1.5800000429153442,
      "start": 1.2799999713897705,
      "word": "so"
    },
    {
      "end": 1.8799999952316284,
      "start": 1.5800000429153442,
      "word": "quietly"
    },
    {
      "end": 2.0999999046325684,
      "start": 1.8799999952316284,
      "word": "you"
    },
    {
      "end": 2.2799999713897705,
      "start": 2.0999999046325684,
      "word": "won't"
    },
    {
      "end": 2.5999999046325684,
      "start": 2.2799999713897705,
      "word": "even"
    },
    {
      "end": 2.7200000286102295,
      "start": 2.5999999046325684,
      "word": "hear"
    },
    {
      "end": 3.1600000858306885,
      "start": 2.7200000286102295,
      "word": "it"
    },
    {
      "end": 4.360000133514404,
      "start": 4.139999866485596,
      "word": "Manufacturing"
    },
    {
      "end": 4.739999771118164,
      "start": 4.360000133514404,
      "word": "plants"
    },
    {
      "end": 5.039999961853027,
      "start": 4.739999771118164,
      "word": "start"
    },
    {
      "end": 5.760000228881836,
      "start": 5.039999961853027,
      "word": "simple"
    },
    {
      "end": 6.099999904632568,
      "start": 5.920000076293945,
      "word": "They"
    },
    {
      "end": 6.159999847412109,
      "start": 6.099999904632568,
      "word": "lease"
    },
    {
      "end": 6.320000171661377,
      "start": 6.159999847412109,
      "word": "a"
    },
    {
      "end": 6.5,
      "start": 6.320000171661377,
      "word": "few"
    },
    {
      "end": 6.960000038146973,
      "start": 6.5,
      "word": "Optimus"
    },
    {
      "end": 7.28000020980835,
      "start": 6.960000038146973,
      "word": "units"
    },
    {
      "end": 7.739999771118164,
      "start": 7.739999771118164,
      "word": "run"
    },
    {
      "end": 8.260000228881836,
      "start": 7.739999771118164,
      "word": "the"
    },
    {
      "end": 8.260000228881836,
      "start": 8.260000228881836,
      "word": "numbers"
    },
    {
      "end": 8.579999923706055,
      "start": 8.5,
      "word": "and"
    },
    {
      "end": 9.119999885559082,
      "start": 8.579999923706055,
      "word": "the"
    },
    {
      "end": 9.140000343322754,
      "start": 9.119999885559082,
      "word": "bath"
    },
    {
      "end": 9.520000457763672,
      "start": 9.140000343322754,
      "word": "is"
    },
    {
      "end": 9.920000076293945,
      "start": 9.520000457763672,
      "word": "undeniable"
    },
    {
      "end": 10.899999618530273,
      "start": 10.720000267028809,
      "word": "Why"
    },
    {
      "end": 11.140000343322754,
      "start": 10.899999618530273,
      "word": "pay"
    },
    {
      "end": 11.460000038146973,
      "start": 11.140000343322754,
      "word": "humans"
    },
    {
      "end": 11.84000015258789,
      "start": 11.460000038146973,
      "word": "40"
    },
    {
      "end": 12.359999656677246,
      "start": 11.84000015258789,
      "word": "an"
    },
    {
      "end": 12.359999656677246,
      "start": 12.359999656677246,
      "word": "hour"
    },
    {
      "end": 12.579999923706055,
      "start": 12.359999656677246,
      "word": "when"
    },
    {
      "end": 12.84000015258789,
      "start": 12.579999923706055,
      "word": "robots"
    },
    {
      "end": 13.119999885559082,
      "start": 12.84000015258789,
      "word": "cost"
    },
    {
      "end": 13.380000114440918,
      "start": 13.119999885559082,
      "word": "8"
    },
    {
      "end": 14.0,
      "start": 13.779999732971191,
      "word": "So"
    },
    {
      "end": 14.380000114440918,
      "start": 14.0,
      "word": "they"
    },
    {
      "end": 14.399999618530273,
      "start": 14.380000114440918,
      "word": "scale"
    },
    {
      "end": 14.640000343322754,
      "start": 14.399999618530273,
      "word": "up"
    },
    {
      "end": 15.140000343322754,
      "start": 14.960000038146973,
      "word": "10"
    },
    {
      "end": 15.399999618530273,
      "start": 15.140000343322754,
      "word": "units"
    },
    {
      "end": 15.640000343322754,
      "start": 15.399999618530273,
      "word": "become"
    },
    {
      "end": 16.100000381469727,
      "start": 15.640000343322754,
      "word": "100"
    },
    {
      "end": 16.860000610351562,
      "start": 16.34000015258789,
      "word": "100"
    },
    {
      "end": 17.15999984741211,
      "start": 16.860000610351562,
      "word": "become"
    },
    {
      "end": 17.579999923706055,
      "start": 17.15999984741211,
      "word": "1"
    },
    {
      "end": 17.639999389648438,
      "start": 17.579999923706055,
      "word": "000"
    },
    {
      "end": 18.579999923706055,
      "start": 18.299999237060547,
      "word": "Then"
    },
    {
      "end": 18.920000076293945,
      "start": 18.579999923706055,
      "word": "something"
    },
    {
      "end": 19.299999237060547,
      "start": 18.920000076293945,
      "word": "shifts"
    },
    {
      "end": 20.079999923706055,
      "start": 19.899999618530273,
      "word": "Tesla"
    },
    {
      "end": 20.5,
      "start": 20.079999923706055,
      "word": "adjusts"
    },
    {
      "end": 20.700000762939453,
      "start": 20.5,
      "word": "the"
    },
    {
      "end": 21.100000381469727,
      "start": 20.700000762939453,
      "word": "subscription"
    },
    {
      "end": 21.420000076293945,
      "start": 21.100000381469727,
      "word": "model"
    },
    {
      "end": 22.420000076293945,
      "start": 22.1200008392334,
      "word": "Monthly"
    },
    {
      "end": 22.579999923706055,
      "start": 22.420000076293945,
      "word": "fees"
    },
    {
      "end": 22.84000015258789,
      "start": 22.579999923706055,
      "word": "climb"
    },
    {
      "end": 23.68000030517578,
      "start": 22.84000015258789,
      "word": "15"
    },
    {
      "end": 24.239999771118164,
      "start": 23.68000030517578,
      "word": "Then"
    },
    {
      "end": 24.68000030517578,
      "start": 24.239999771118164,
      "word": "20"
    },
    {
      "end": 25.3799991607666,
      "start": 25.280000686645508,
      "word": "Factory"
    },
    {
      "end": 25.6200008392334,
      "start": 25.3799991607666,
      "word": "owners"
    },
    {
      "end": 25.979999542236328,
      "start": 25.6200008392334,
      "word": "grumble"
    },
    {
      "end": 26.459999084472656,
      "start": 26.239999771118164,
      "word": "But"
    },
    {
      "end": 26.6200008392334,
      "start": 26.459999084472656,
      "word": "what's"
    },
    {
      "end": 26.799999237060547,
      "start": 26.6200008392334,
      "word": "the"
    },
    {
      "end": 27.18000030517578,
      "start": 26.799999237060547,
      "word": "alternative"
    },
    {
      "end": 28.1200008392334,
      "start": 27.84000015258789,
      "word": "Fire"
    },
    {
      "end": 28.360000610351562,
      "start": 28.1200008392334,
      "word": "the"
    },
    {
      "end": 28.68000030517578,
      "start": 28.360000610351562,
      "word": "machines"
    },
    {
      "end": 28.979999542236328,
      "start": 28.68000030517578,
      "word": "and"
    },
    {
      "end": 29.260000228881836,
      "start": 28.979999542236328,
      "word": "post"
    },
    {
      "end": 29.420000076293945,
      "start": 29.260000228881836,
      "word": "job"
    },
    {
      "end": 29.780000686645508,
      "start": 29.420000076293945,
      "word": "listings"
    },
    {
      "end": 30.700000762939453,
      "start": 30.520000457763672,
      "word": "Retrain"
    },
    {
      "end": 31.100000381469727,
      "start": 30.700000762939453,
      "word": "a"
    },
    {
      "end": 31.15999984741211,
      "start": 31.100000381469727,
      "word": "human"
    },
    {
      "end": 31.579999923706055,
      "start": 31.15999984741211,
      "word": "workforce"
    },
    {
      "end": 32.08000183105469,
      "start": 31.579999923706055,
      "word": "that's"
    },
    {
      "end": 32.08000183105469,
      "start": 32.08000183105469,
      "word": "moved"
    },
    {
      "end": 32.279998779296875,
      "start": 32.08000183105469,
      "word": "on"
    },
    {
      "end": 32.380001068115234,
      "start": 32.279998779296875,
      "word": "to"
    },
    {
      "end": 32.619998931884766,
      "start": 32.380001068115234,
      "word": "other"
    },
    {
      "end": 32.939998626708984,
      "start": 32.619998931884766,
      "word": "industries"
    },
    {
      "end": 33.79999923706055,
      "start": 33.65999984741211,
      "word": "The"
    },
    {
      "end": 34.02000045776367,
      "start": 33.79999923706055,
      "word": "cost"
    },
    {
      "end": 34.220001220703125,
      "start": 34.02000045776367,
      "word": "of"
    },
    {
      "end": 34.459999084472656,
      "start": 34.220001220703125,
      "word": "switching"
    },
    {
      "end": 34.900001525878906,
      "start": 34.459999084472656,
      "word": "back"
    },
    {
      "end": 35.31999969482422,
      "start": 34.900001525878906,
      "word": "now"
    },
    {
      "end": 35.459999084472656,
      "start": 35.31999969482422,
      "word": "exceeds"
    },
    {
      "end": 35.70000076293945,
      "start": 35.459999084472656,
      "word": "the"
    },
    {
      "end": 35.97999954223633,
      "start": 35.70000076293945,
      "word": "cost"
    },
    {
      "end": 36.15999984741211,
      "start": 35.97999954223633,
      "word": "of"
    },
    {
      "end": 36.380001068115234,
      "start": 36.15999984741211,
      "word": "staying"
    },
    {
      "end": 36.599998474121094,
      "start": 36.380001068115234,
      "word": "locked"
    },
    {
      "end": 36.880001068115234,
      "start": 36.599998474121094,
      "word": "in"
    },
    {
      "end": 37.599998474121094,
      "start": 37.52000045776367,
      "word": "This"
    },
    {
      "end": 37.779998779296875,
      "start": 37.599998474121094,
      "word": "is"
    },
    {
      "end": 38.040000915527344,
      "start": 37.779998779296875,
      "word": "the"
    },
    {
      "end": 38.380001068115234,
      "start": 38.040000915527344,
      "word": "dependency"
    },
    {
      "end": 38.86000061035156,
      "start": 38.380001068115234,
      "word": "spiral"
    },
    {
      "end": 39.08000183105469,
      "start": 39.040000915527344,
      "word": "and"
    },
    {
      "end": 39.31999969482422,
      "start": 39.08000183105469,
      "word": "it's"
    },
    {
      "end": 40.439998626708984,
      "start": 39.31999969482422,
      "word": "devastatingly"
    },
    {
      "end": 40.439998626708984,
      "start": 40.439998626708984,
      "word": "effective"
    },
    {
      "end": 41.52000045776367,
      "start": 41.279998779296875,
      "word": "Every"
    },
    {
      "end": 41.91999816894531,
      "start": 41.52000045776367,
      "word": "price"
    },
    {
      "end": 42.2599983215332,
      "start": 41.91999816894531,
      "word": "increase"
    },
    {
      "end": 42.540000915527344,
      "start": 42.2599983215332,
      "word": "gets"
    },
    {
      "end": 42.91999816894531,
      "start": 42.540000915527344,
      "word": "absorbed"
    },
    {
      "end": 43.2599983215332,
      "start": 42.91999816894531,
      "word": "because"
    },
    {
      "end": 43.560001373291016,
      "start": 43.2599983215332,
      "word": "the"
    },
    {
      "end": 43.619998931884766,
      "start": 43.560001373291016,
      "word": "pain"
    },
    {
      "end": 44.20000076293945,
      "start": 43.619998931884766,
      "word": "of"
    },
    {
      "end": 44.20000076293945,
      "start": 44.20000076293945,
      "word": "leaving"
    },
    {
      "end": 44.599998474121094,
      "start": 44.20000076293945,
      "word": "hurts"
    },
    {
      "end": 44.959999084472656,
      "start": 44.599998474121094,
      "word": "more"
    },
    {
      "end": 45.08000183105469,
      "start": 44.959999084472656,
      "word": "than"
    },
    {
      "end": 45.5,
      "start": 45.08000183105469,
      "word": "the"
    },
    {
      "end": 45.5,
      "start": 45.5,
      "word": "pain"
    },
    {
      "end": 45.86000061035156,
      "start": 45.5,
      "word": "of"
    },
    {
      "end": 46.29999923706055,
      "start": 45.86000061035156,
      "word": "paying"
    },
    {
      "end": 47.459999084472656,
      "start": 47.20000076293945,
      "word": "Tesla"
    },
    {
      "end": 47.7400016784668,
      "start": 47.459999084472656,
      "word": "doesn't"
    },
    {
      "end": 48.02000045776367,
      "start": 47.7400016784668,
      "word": "need"
    },
    {
      "end": 48.31999969482422,
      "start": 48.02000045776367,
      "word": "to"
    },
    {
      "end": 48.31999969482422,
      "start": 48.31999969482422,
      "word": "own"
    },
    {
      "end": 48.58000183105469,
      "start": 48.31999969482422,
      "word": "your"
    },
    {
      "end": 48.81999969482422,
      "start": 48.58000183105469,
      "word": "factory"
    },
    {
      "end": 49.41999816894531,
      "start": 49.31999969482422,
      "word": "They"
    },
    {
      "end": 49.720001220703125,
      "start": 49.41999816894531,
      "word": "just"
    },
    {
      "end": 49.79999923706055,
      "start": 49.720001220703125,
      "word": "need"
    },
    {
      "end": 50.099998474121094,
      "start": 49.79999923706055,
      "word": "to"
    },
    {
      "end": 50.099998474121094,
      "start": 50.099998474121094,
      "word": "own"
    },
    {
      "end": 50.439998626708984,
      "start": 50.099998474121094,
      "word": "something"
    },
    {
      "end": 50.65999984741211,
      "start": 50.439998626708984,
      "word": "your"
    },
    {
      "end": 50.880001068115234,
      "start": 50.65999984741211,
      "word": "factory"
    },
    {
      "end": 51.18000030517578,
      "start": 50.880001068115234,
      "word": "cannot"
    },
    {
      "end": 51.52000045776367,
      "start": 51.18000030517578,
      "word": "function"
    },
    {
      "end": 51.939998626708984,
      "start": 51.52000045776367,
      "word": "without"
    },
    {
      "end": 52.880001068115234,
      "start": 52.31999969482422,
      "word": "The"
    },
    {
      "end": 53.08000183105469,
      "start": 52.880001068115234,
      "word": "rent"
    },
    {
      "end": 53.560001373291016,
      "start": 53.08000183105469,
      "word": "extraction"
    },
    {
      "end": 53.939998626708984,
      "start": 53.560001373291016,
      "word": "phase"
    },
    {
      "end": 54.18000030517578,
      "start": 53.939998626708984,
      "word": "has"
    },
    {
      "end": 54.439998626708984,
      "start": 54.18000030517578,
      "word": "begun"
    },
    {
      "end": 54.959999084472656,
      "start": 54.84000015258789,
      "word": "and"
    },
    {
      "end": 55.20000076293945,
      "start": 54.959999084472656,
      "word": "here's"
    },
    {
      "end": 55.36000061035156,
      "start": 55.20000076293945,
      "word": "what"
    },
    {
      "end": 55.540000915527344,
      "start": 55.36000061035156,
      "word": "makes"
    },
    {
      "end": 55.7400016784668,
      "start": 55.540000915527344,
      "word": "it"
    },
    {
      "end": 56.040000915527344,
      "start": 55.7400016784668,
      "word": "permanent"
    },
    {
      "end": 56.70000076293945,
      "start": 56.41999816894531,
      "word": "The"
    },
    {
      "end": 57.02000045776367,
      "start": 56.70000076293945,
      "word": "longer"
    },
    {
      "end": 57.29999923706055,
      "start": 57.02000045776367,
      "word": "you"
    },
    {
      "end": 57.52000045776367,
      "start": 57.29999923706055,
      "word": "stay"
    },
    {
      "end": 57.959999084472656,
      "start": 57.63999938964844,
      "word": "the"
    },
    {
      "end": 58.13999938964844,
      "start": 57.959999084472656,
      "word": "deeper"
    },
    {
      "end": 58.63999938964844,
      "start": 58.13999938964844,
      "word": "you"
    },
    {
      "end": 58.63999938964844,
      "start": 58.63999938964844,
      "word": "sink"
    },
    {
      "end": 59.2599983215332,
      "start": 59.13999938964844,
      "word": "Your"
    },
    {
      "end": 59.52000045776367,
      "start": 59.2599983215332,
      "word": "human"
    },
    {
      "end": 59.939998626708984,
      "start": 59.52000045776367,
      "word": "expertise"
    },
    {
      "end": 60.5,
      "start": 59.939998626708984,
      "word": "erodes"
    },
    {
      "end": 61.20000076293945,
      "start": 61.02000045776367,
      "word": "Your"
    },
    {
      "end": 61.720001220703125,
      "start": 61.20000076293945,
      "word": "alternatives"
    },
    {
      "end": 62.18000030517578,
      "start": 61.720001220703125,
      "word": "vanish"
    },
    {
      "end": 62.900001525878906,
      "start": 62.779998779296875,
      "word": "You're"
    },
    {
      "end": 62.97999954223633,
      "start": 62.900001525878906,
      "word": "not"
    },
    {
      "end": 63.20000076293945,
      "start": 62.97999954223633,
      "word": "a"
    },
    {
      "end": 63.47999954223633,
      "start": 63.20000076293945,
      "word": "customer"
    },
    {
      "end": 63.959999084472656,
      "start": 63.47999954223633,
      "word": "anymore"
    },
    {
      "end": 64.5,
      "start": 64.33999633789062,
      "word": "You're"
    },
    {
      "end": 64.68000030517578,
      "start": 64.5,
      "word": "a"
    },
    {
      "end": 65.13999938964844,
      "start": 64.68000030517578,
      "word": "subscriber"
    },
    {
      "end": 65.4800033569336,
      "start": 65.13999938964844,
      "word": "who"
    },
    {
      "end": 65.76000213623047,
      "start": 65.4800033569336,
      "word": "forgot"
    },
    {
      "end": 66.04000091552734,
      "start": 65.76000213623047,
      "word": "how"
    },
    {
      "end": 66.26000213623047,
      "start": 66.04000091552734,
      "word": "to"
    },
    {
      "end": 66.4800033569336,
      "start": 66.26000213623047,
      "word": "leave"
    }
  ],
  "task": "transcribe"
}